{
  "stats": {
    "2023-09-11": {
      "Entrust": 6
    },
    "2023-09-12": {
      "Entrust": 3
    },
    "2023-09-26": {
      "Entrust": 3
    },
    "2023-11-01": {
      "Entrust": 9
    },
    "2023-11-27": {
      "Entrust": 4
    },
    "2024-01-03": {
      "Entrust": 1
    },
    "2024-01-05": {
      "Entrust": 1
    },
    "2024-01-15": {
      "Entrust": 2
    },
    "2024-01-25": {
      "Entrust": 3
    },
    "2024-04-03": {
      "Entrust": 3
    },
    "2024-04-10": {
      "Entrust": 2
    },
    "2024-04-22": {
      "Entrust": 5
    },
    "2024-05-17": {
      "Entrust": 2
    },
    "2024-06-12": {
      "Entrust": 3
    },
    "2024-06-18": {
      "Entrust": 1
    },
    "2024-06-28": {
      "Entrust": 5
    },
    "2024-07-02": {
      "Entrust": 1
    },
    "2024-07-03": {
      "Entrust": 1
    },
    "2024-07-04": {
      "Entrust": 1
    },
    "2024-07-16": {
      "Entrust": 3
    },
    "2024-07-23": {
      "Let's Encrypt": 1
    },
    "2024-08-06": {
      "Entrust": 5
    },
    "2024-08-20": {
      "Entrust": 2
    },
    "2024-08-23": {
      "Entrust": 28
    },
    "2024-08-29": {
      "Entrust": 2
    },
    "2024-09-03": {
      "Entrust": 2
    },
    "2024-09-12": {
      "Entrust": 3
    },
    "2024-09-22": {
      "Let's Encrypt": 1
    },
    "2024-10-17": {
      "Entrust": 3
    },
    "2024-11-20": {
      "Let's Encrypt": 1
    }
  },
  "errors": []
}